pneuro/__init__.py
pneuro/__main__.py
pneuro/appLogger.py
pneuro/classificationModels.py
pneuro/data_loader.py
pneuro/file_methods.py
pneuro/preProcess.py
pneuro/predict.py
pneuro/regressionModels.py
pneuro/visualization.py
pneuro/logs/RegressionTrainingLogs.txt
pneuro/logs/classificationTrainingLogs.txt
pneuro/logs/dataLoadLogs.txt
pneuro/logs/dataPreprocessingLogs.txt
pneuro/logs/dataVisualizationLogs.txt
pneuro/logs/fileOperationLogs.txt
pneuro/logs/predictionLogs.txt
pneuro/logs/test.txt
pneuro/models/RandomForest.sav
pneuro/static/assets/demo/chart-area-demo.js
pneuro/static/assets/demo/chart-bar-demo.js
pneuro/static/assets/demo/chart-pie-demo.js
pneuro/static/assets/demo/datatables-demo.js
pneuro/static/assets/img/error-404-monochrome.svg
pneuro/static/css/styles.css
pneuro/static/graphs/correlation.png
pneuro/static/graphs/test.jpg
pneuro/static/js/scripts.js
pneuro/static/scripts/build-assets.js
pneuro/static/scripts/build-pug.js
pneuro/static/scripts/build-scripts.js
pneuro/static/scripts/build-scss.js
pneuro/static/scripts/clean.js
pneuro/static/scripts/render-assets.js
pneuro/static/scripts/render-pug.js
pneuro/static/scripts/render-scripts.js
pneuro/static/scripts/render-scss.js
pneuro/static/scripts/sb-watch.js
pneuro/static/scripts/start-debug.js
pneuro/static/scripts/start.js
pneuro/templates/401.html
pneuro/templates/404.html
pneuro/templates/500.html
pneuro/templates/charts.html
pneuro/templates/index.html
pneuro/templates/layout-sidenav-light.html
pneuro/templates/layout-static.html
pneuro/templates/login.html
pneuro/templates/model_report_classification.html
pneuro/templates/model_report_regression.html
pneuro/templates/password.html
pneuro/templates/prediction.html
pneuro/templates/prediction_results.html
pneuro/templates/register.html
pneuro/templates/tables.html
pneuro-1.3.7.0.0.dist-info/LICENSE.txt
pneuro-1.3.7.0.0.dist-info/METADATA
pneuro-1.3.7.0.0.dist-info/WHEEL
pneuro-1.3.7.0.0.dist-info/entry_points.txt
pneuro-1.3.7.0.0.dist-info/top_level.txt
pneuro-1.3.7.0.0.dist-info/RECORD
