Metadata-Version: 2.1
Name: pneuro
Version: 1.3.7.0.0
Summary: Python API for Automated ML
Home-page: http://autoneuro.ml
Author: iNeuron
Author-email: 
Maintainer: iNeuron
Maintainer-email: support@iNeuron.com
License: MIT
Project-URL: Documentation, https://github.com/nabeelfahmi12/AutoNeuro-Documentation
Project-URL: Source Code, https://github.com/viratsagar/Autoneuro
Platform: UNKNOWN
Classifier: Intended Audience :: Developers 
Classifier: Intended Audience :: End Users/Desktop
Classifier: License :: OSI Approved :: MIT License
Classifier: Programming Language :: Python
Classifier: Topic :: Software Development 
Classifier: Operating System :: Microsoft :: Windows
Classifier: Operating System :: Unix
Classifier: Operating System :: MacOS
Classifier: Programming Language :: Python
Requires-Python: >=3.6
Requires-Dist: APScheduler (==3.6.3)
Requires-Dist: asgiref (==3.2.10)
Requires-Dist: certifi (==2020.6.20)
Requires-Dist: click (==7.1.2)
Requires-Dist: colorhash (==1.0.2)
Requires-Dist: configparser (==4.0.2)
Requires-Dist: cycler (==0.10.0)
Requires-Dist: Django (==3.0.8)
Requires-Dist: Flask (==1.1.2)
Requires-Dist: Flask-Cors (==3.0.8)
Requires-Dist: Flask-MonitoringDashboard (==3.0.6)
Requires-Dist: image (==1.5.32)
Requires-Dist: imbalanced-learn (==0.7.0)
Requires-Dist: imblearn (==0.0)
Requires-Dist: itsdangerous (==1.1.0)
Requires-Dist: Jinja2 (==2.11.2)
Requires-Dist: joblib (==0.16.0)
Requires-Dist: kiwisolver (==1.1.0)
Requires-Dist: MarkupSafe (==1.1.1)
Requires-Dist: matplotlib (==3.0.3)
Requires-Dist: numpy (==1.19.0)
Requires-Dist: pandas (==1.0.5)
Requires-Dist: patsy (==0.5.1)
Requires-Dist: Pillow (==7.2.0)
Requires-Dist: plotly (==4.9.0)
Requires-Dist: psutil (==5.7.2)
Requires-Dist: pymongo (==3.10.1)
Requires-Dist: pyparsing (==2.4.6)
Requires-Dist: python-dateutil (==2.8.1)
Requires-Dist: pytz (==2020.1)
Requires-Dist: retrying (==1.3.3)
Requires-Dist: scikit-learn (==0.23.1)
Requires-Dist: scipy (==1.5.1)
Requires-Dist: seaborn (==0.10.1)
Requires-Dist: six (==1.15.0)
Requires-Dist: SQLAlchemy (==1.3.13)
Requires-Dist: sqlparse (==0.3.1)
Requires-Dist: statsmodels (==0.11.1)
Requires-Dist: threadpoolctl (==2.1.0)
Requires-Dist: tzlocal (==2.0.0)
Requires-Dist: Werkzeug (==1.0.1)
Requires-Dist: wincertstore (==0.2)
Requires-Dist: xgboost
Provides-Extra: examples
Requires-Dist: matplotlib ; extra == 'examples'
Requires-Dist: jupyter ; extra == 'examples'
Requires-Dist: notebook ; extra == 'examples'
Requires-Dist: ipykernel ; extra == 'examples'
Requires-Dist: seaborn ; extra == 'examples'
Provides-Extra: examples_unix
Requires-Dist: fanova ; extra == 'examples_unix'
Provides-Extra: test
Requires-Dist: matplotlib ; extra == 'test'
Requires-Dist: pytest ; extra == 'test'
Requires-Dist: pytest-xdist ; extra == 'test'
